gitcal/__init__.py
gitcal/__main__.py
gitcal/args.py
gitcal/gitcal.py
gitcal/gitcommit.py
gitcal/table.py
gitcal/tableconfig.py
gitcal-0.0.3.dist-info/LICENSE
gitcal-0.0.3.dist-info/METADATA
gitcal-0.0.3.dist-info/WHEEL
gitcal-0.0.3.dist-info/entry_points.txt
gitcal-0.0.3.dist-info/top_level.txt
gitcal-0.0.3.dist-info/RECORD
