Metadata-Version: 2.1
Name: gitcal
Version: 0.0.3
Summary: Visualize when git commits were made in a repository in a calendar-like format.
Home-page: https://github.com/WiLGYSeF/gitcal
Author: wilgysef
Author-email: wilgysef@gmail.com
License: UNKNOWN
Project-URL: Bug Tracker, https://github.com/WiLGYSeF/gitcal/issues
Platform: UNKNOWN
Classifier: Programming Language :: Python :: 3
Classifier: License :: OSI Approved :: MIT License
Classifier: Operating System :: OS Independent
Requires-Python: >=3.6
License-File: LICENSE
